README.md
setup.cfg
setup.py
antcat/__init__.py
antcat/catalog.py
antcat_py.egg-info/PKG-INFO
antcat_py.egg-info/SOURCES.txt
antcat_py.egg-info/dependency_links.txt
antcat_py.egg-info/requires.txt
antcat_py.egg-info/top_level.txt
api/__init__.py
api/call.py
api/helper.py
api/models.py